MANIFEST.in
README.md
extra-requirements.txt
fastentrypoints.py
setup.py
cli/__init__.py
cli/api.py
cli/autocomplete.py
cli/export.py
daemon/__init__.py
daemon/excepts.py
daemon/parser.py
daemon/api/__init__.py
daemon/api/endpoints/__init__.py
daemon/api/endpoints/flow.py
daemon/api/endpoints/logs.py
daemon/api/endpoints/pea.py
daemon/api/endpoints/pod.py
daemon/api/endpoints/workspace.py
daemon/models/__init__.py
daemon/models/custom.py
daemon/models/status.py
daemon/stores/__init__.py
daemon/stores/base.py
daemon/stores/flow.py
daemon/stores/helper.py
daemon/stores/pea.py
daemon/stores/pod.py
daemon/stores/workspace.py
jina/__init__.py
jina/checker.py
jina/enums.py
jina/excepts.py
jina/helper.py
jina/importer.py
jina/clients/__init__.py
jina/clients/asyncio.py
jina/clients/base.py
jina/clients/grpc.py
jina/clients/helper.py
jina/clients/mixin.py
jina/clients/websocket.py
jina/clients/request/__init__.py
jina/clients/request/asyncio.py
jina/clients/request/helper.py
jina/executors/__init__.py
jina/executors/decorators.py
jina/executors/metas.py
jina/flow/__init__.py
jina/flow/base.py
jina/flow/builder.py
jina/helloworld/__init__.py
jina/helloworld/fork.py
jina/helloworld/__pycache__/__init__.cpython-37.pyc
jina/helloworld/__pycache__/fork.cpython-37.pyc
jina/helloworld/__pycache__/helper.cpython-37.pyc
jina/helloworld/chatbot/__init__.py
jina/helloworld/chatbot/app.py
jina/helloworld/chatbot/my_executors.py
jina/helloworld/chatbot/__pycache__/__init__.cpython-37.pyc
jina/helloworld/chatbot/__pycache__/app.cpython-37.pyc
jina/helloworld/chatbot/__pycache__/my_executors.cpython-37.pyc
jina/helloworld/chatbot/static/index.html
jina/helloworld/chatbot/static/license.txt
jina/helloworld/chatbot/static/script.js
jina/helloworld/chatbot/static/style.css
jina/helloworld/fashion/__init__.py
jina/helloworld/fashion/app.py
jina/helloworld/fashion/demo.html
jina/helloworld/fashion/helper.py
jina/helloworld/fashion/my_executors.py
searchai.egg-info/PKG-INFO
searchai.egg-info/SOURCES.txt
searchai.egg-info/dependency_links.txt
searchai.egg-info/entry_points.txt
searchai.egg-info/not-zip-safe
searchai.egg-info/requires.txt
searchai.egg-info/top_level.txt