Metadata-Version: 2.1
Name: searchai
Version: 0.0.1
Summary: Jina is geared towards building search-as-a-service systems for any kind of data in just minutes.
Home-page: https://github.com/jina-ai/jina/
Author: Jina Dev Team
Author-email: dev-team@jina.ai
License: Apache 2.0
Download-URL: https://github.com/jina-ai/jina/tags
Project-URL: Documentation, https://docs2.jina.ai
Project-URL: Source, https://github.com/jina-ai/jina/
Project-URL: Tracker, https://github.com/jina-ai/jina/issues
Keywords: jina cloud-native neural-search query search index elastic neural-network encoding embedding serving docker container image video audio deep-learning
Platform: UNKNOWN
Classifier: Development Status :: 5 - Production/Stable
Classifier: Intended Audience :: Developers
Classifier: Intended Audience :: Education
Classifier: Intended Audience :: Science/Research
Classifier: Programming Language :: Python :: 3.7
Classifier: Programming Language :: Python :: 3.8
Classifier: Programming Language :: Python :: 3.9
Classifier: Programming Language :: Unix Shell
Classifier: Environment :: Console
Classifier: License :: OSI Approved :: Apache Software License
Classifier: Operating System :: OS Independent
Classifier: Topic :: Database :: Database Engines/Servers
Classifier: Topic :: Scientific/Engineering :: Artificial Intelligence
Classifier: Topic :: Internet :: WWW/HTTP :: Indexing/Search
Classifier: Topic :: Scientific/Engineering :: Image Recognition
Classifier: Topic :: Multimedia :: Video
Classifier: Topic :: Scientific/Engineering
Classifier: Topic :: Scientific/Engineering :: Mathematics
Classifier: Topic :: Software Development
Classifier: Topic :: Software Development :: Libraries
Classifier: Topic :: Software Development :: Libraries :: Python Modules
Provides-Extra: index
Provides-Extra: cicd
Provides-Extra: scipy
Provides-Extra: numeric
Provides-Extra: py37
Provides-Extra: py38
Provides-Extra: test
Provides-Extra: multimodal
Provides-Extra: daemon
Provides-Extra: devel
Provides-Extra: fastapi
Provides-Extra: chatbot
Provides-Extra: http
Provides-Extra: uvicorn
Provides-Extra: dashboard
Provides-Extra: fluent-logger
Provides-Extra: logging
Provides-Extra: sse
Provides-Extra: nmslib
Provides-Extra: hub
Provides-Extra: docker
Provides-Extra: network
Provides-Extra: torch
Provides-Extra: framework
Provides-Extra: transformers
Provides-Extra: nlp
Provides-Extra: flair
Provides-Extra: paddlepaddle
Provides-Extra: paddlehub
Provides-Extra: tensorflow
Provides-Extra: tensorflow-hub
Provides-Extra: cv
Provides-Extra: torchvision
Provides-Extra: onnx
Provides-Extra: onnxruntime
Provides-Extra: Pillow
Provides-Extra: annoy
Provides-Extra: sklearn
Provides-Extra: plyvel
Provides-Extra: jieba
Provides-Extra: perf
Provides-Extra: lz4
Provides-Extra: gevent
Provides-Extra: python-magic
Provides-Extra: pymilvus
Provides-Extra: deepsegment
Provides-Extra: ngt
Provides-Extra: librosa
Provides-Extra: audio
Provides-Extra: uvloop
Provides-Extra: numpy
Provides-Extra: core
Provides-Extra: pyzmq
Provides-Extra: protobuf
Provides-Extra: grpcio
Provides-Extra: pyyaml
Provides-Extra: tornado
Provides-Extra: cookiecutter
Provides-Extra: pytest
Provides-Extra: pytest-xdist
Provides-Extra: pytest-timeout
Provides-Extra: pytest-mock
Provides-Extra: pytest-cov
Provides-Extra: pytest-repeat
Provides-Extra: pytest-asyncio
Provides-Extra: pytest-xprocess
Provides-Extra: pytest-reraise
Provides-Extra: flaky
Provides-Extra: mock
Provides-Extra: requests
Provides-Extra: prettytable
Provides-Extra: optimizer
Provides-Extra: optuna
Provides-Extra: ws
Provides-Extra: websockets
Provides-Extra: wsproto
Provides-Extra: pydantic
Provides-Extra: python-multipart
Provides-Extra: aiofiles
Provides-Extra: pytest-custom_exit_code
Provides-Extra: bs4
Provides-Extra: aiostream
Provides-Extra: click
Provides-Extra: jsonschema
Provides-Extra: dgl
Provides-Extra: all
Provides-Extra: match-py-ver
